sparc_custom_tabs/__init__.py
sparc_custom_tabs/frontend/build/asset-manifest.json
sparc_custom_tabs/frontend/build/bootstrap.min.css
sparc_custom_tabs/frontend/build/index.html
sparc_custom_tabs/frontend/build/static/css/main.ff48f0d8.css
sparc_custom_tabs/frontend/build/static/js/main.2385ff70.js
sparc_custom_tabs/frontend/build/static/js/main.2385ff70.js.LICENSE.txt
sparc_custom_tabs/frontend/node_modules/flatted/python/flatted.py
sparc_custom_tabs-1.0.0.dist-info/licenses/LICENSE
sparc_custom_tabs-1.0.0.dist-info/METADATA
sparc_custom_tabs-1.0.0.dist-info/WHEEL
sparc_custom_tabs-1.0.0.dist-info/top_level.txt
sparc_custom_tabs-1.0.0.dist-info/RECORD
