Metadata-Version: 2.4
Name: sparc_custom_tabs
Version: 1.0.0
Summary: custom tabs component for sparc app derived from github: Mohamed-512's tab bar component
Author-email: Nick Fitzhugh <nicholas.j.fitzhugh@gmail.com>
Project-URL: Repository, https://github.com/nfitzhugh-us/sparc_custom_tabs
Keywords: Python,Streamlit,React,JavaScript
Classifier: Programming Language :: Python :: 3
Classifier: License :: OSI Approved :: MIT License
Classifier: Operating System :: OS Independent
Requires-Python: >=3.6
License-File: LICENSE
Requires-Dist: streamlit>=1.40.1
Dynamic: license-file
